{
  "project_info": {
    "project_number": "",
    "firebase_url": "",
    "project_id": "",
    "storage_bucket": ""
  },
  "client": [
    {
      "client_info": {
        "mobilesdk_app_id": "1:123456789012:android:1234567890123456789012",
        "android_client_info": {
          "package_name": "com.codewithkael.javawebrtcyoutube"
        }
      },
      "oauth_client": [
        {
          "client_id": "",
          "client_type": 3
        }
      ],
      "api_key": [
        {
          "current_key": ""
        }
      ],
      "services": {
        "appinvite_service": {
          "other_platform_oauth_client": [
            {
              "client_id": "",
              "client_type": 3
            },
            {
              "client_id": "",
              "client_type": 2,
              "ios_info": {
                "bundle_id": "net.openkochi.yatri.debug"
              }
            }
          ]
        }
      }
    },
    {
      "client_info": {
        "mobilesdk_app_id": "1:123456789012:android:1234567890123456789012",
        "android_client_info": {
          "package_name": "com.example.fcm"
        }
      },
      "oauth_client": [
        {
          "client_id": "",
          "client_type": 3
        }
      ],
      "api_key": [
        {
          "current_key": ""
        }
      ],
      "services": {
        "appinvite_service": {
          "other_platform_oauth_client": [
            {
              "client_id": "",
              "client_type": 3
            },
            {
              "client_id": "",
              "client_type": 2,
              "ios_info": {
                "bundle_id": "net.openkochi.yatri.debug"
              }
            }
          ]
        }
      }
    },
    {
      "client_info": {
        "mobilesdk_app_id": "1:123456789012:android:1234567890123456789012",
        "android_client_info": {
          "package_name": "com.webengage.sample"
        }
      },
      "oauth_client": [
        {
          "client_id": "",
          "client_type": 3
        }
      ],
      "api_key": [
        {
          "current_key": ""
        }
      ],
      "services": {
        "appinvite_service": {
          "other_platform_oauth_client": [
            {
              "client_id": "",
              "client_type": 3
            },
            {
              "client_id": "",
              "client_type": 2,
              "ios_info": {
                "bundle_id": "net.openkochi.yatri.debug"
              }
            }
          ]
        }
      }
    },
    {
      "client_info": {
        "mobilesdk_app_id": "1:123456789012:android:1234567890123456789012",
        "android_client_info": {
          "package_name": "in.juspay.beckn.customer"
        }
      },
      "oauth_client": [
        {
          "client_id": "",
          "client_type": 3
        }
      ],
      "api_key": [
        {
          "current_key": ""
        }
      ],
      "services": {
        "appinvite_service": {
          "other_platform_oauth_client": [
            {
              "client_id": "",
              "client_type": 3
            },
            {
              "client_id": "",
              "client_type": 2,
              "ios_info": {
                "bundle_id": "net.openkochi.yatri.debug"
              }
            }
          ]
        }
      }
    },
    {
      "client_info": {
        "mobilesdk_app_id": "1:123456789012:android:1234567890123456789012",
        "android_client_info": {
          "package_name": "in.juspay.beckn.transporter"
        }
      },
      "oauth_client": [
        {
          "client_id": "",
          "client_type": 1,
          "android_info": {
            "package_name": "in.juspay.beckn.transporter",
            "certificate_hash": ""
          }
        },
        {
          "client_id": "",
          "client_type": 3
        }
      ],
      "api_key": [
        {
          "current_key": ""
        }
      ],
      "services": {
        "appinvite_service": {
          "other_platform_oauth_client": [
            {
              "client_id": "",
              "client_type": 3
            },
            {
              "client_id": "",
              "client_type": 2,
              "ios_info": {
                "bundle_id": "net.openkochi.yatri.debug"
              }
            }
          ]
        }
      }
    },
    {
      "client_info": {
        "mobilesdk_app_id": "1:123456789012:android:1234567890123456789012",
        "android_client_info": {
          "package_name": "in.juspay.becknui"
        }
      },
      "oauth_client": [
        {
          "client_id": "",
          "client_type": 3
        }
      ],
      "api_key": [
        {
          "current_key": ""
        }
      ],
      "services": {
        "appinvite_service": {
          "other_platform_oauth_client": [
            {
              "client_id": "",
              "client_type": 3
            },
            {
              "client_id": "",
              "client_type": 2,
              "ios_info": {
                "bundle_id": "net.openkochi.yatri.debug"
              }
            }
          ]
        }
      }
    },
    {
      "client_info": {
        "mobilesdk_app_id": "1:123456789012:android:1234567890123456789012",
        "android_client_info": {
          "package_name": "in.juspay.becknuser"
        }
      },
      "oauth_client": [
        {
          "client_id": "",
          "client_type": 1,
          "android_info": {
            "package_name": "in.juspay.becknuser",
            "certificate_hash": ""
          }
        },
        {
          "client_id": "",
          "client_type": 3
        }
      ],
      "api_key": [
        {
          "current_key": ""
        }
      ],
      "services": {
        "appinvite_service": {
          "other_platform_oauth_client": [
            {
              "client_id": "",
              "client_type": 3
            },
            {
              "client_id": "",
              "client_type": 2,
              "ios_info": {
                "bundle_id": "net.openkochi.yatri.debug"
              }
            }
          ]
        }
      }
    },
    {
      "client_info": {
        "mobilesdk_app_id": "1:123456789012:android:1234567890123456789012",
        "android_client_info": {
          "package_name": "in.juspay.jatrisaathi.debug"
        }
      },
      "oauth_client": [
        {
          "client_id": "",
          "client_type": 3
        }
      ],
      "api_key": [
        {
          "current_key": ""
        }
      ],
      "services": {
        "appinvite_service": {
          "other_platform_oauth_client": [
            {
              "client_id": "",
              "client_type": 3
            },
            {
              "client_id": "",
              "client_type": 2,
              "ios_info": {
                "bundle_id": "net.openkochi.yatri.debug"
              }
            }
          ]
        }
      }
    },
    {
      "client_info": {
        "mobilesdk_app_id": "1:123456789012:android:1234567890123456789012",
        "android_client_info": {
          "package_name": "in.juspay.jatrisaathidriver.debug"
        }
      },
      "oauth_client": [
        {
          "client_id": "",
          "client_type": 3
        }
      ],
      "api_key": [
        {
          "current_key": ""
        }
      ],
      "services": {
        "appinvite_service": {
          "other_platform_oauth_client": [
            {
              "client_id": "",
              "client_type": 3
            },
            {
              "client_id": "",
              "client_type": 2,
              "ios_info": {
                "bundle_id": "net.openkochi.yatri.debug"
              }
            }
          ]
        }
      }
    },
    {
      "client_info": {
        "mobilesdk_app_id": "1:123456789012:android:1234567890123456789012",
        "android_client_info": {
          "package_name": "in.juspay.nammayatri.debug"
        }
      },
      "oauth_client": [
        {
          "client_id": "",
          "client_type": 1,
          "android_info": {
            "package_name": "in.juspay.nammayatri.debug",
            "certificate_hash": ""
          }
        },
        {
          "client_id": "",
          "client_type": 3
        }
      ],
      "api_key": [
        {
          "current_key": ""
        }
      ],
      "services": {
        "appinvite_service": {
          "other_platform_oauth_client": [
            {
              "client_id": "",
              "client_type": 3
            },
            {
              "client_id": "",
              "client_type": 2,
              "ios_info": {
                "bundle_id": "net.openkochi.yatri.debug"
              }
            }
          ]
        }
      }
    },
    {
      "client_info": {
        "mobilesdk_app_id": "1:123456789012:android:1234567890123456789012",
        "android_client_info": {
          "package_name": "in.juspay.nammayatripartner"
        }
      },
      "oauth_client": [
        {
          "client_id": "",
          "client_type": 3
        }
      ],
      "api_key": [
        {
          "current_key": ""
        }
      ],
      "services": {
        "appinvite_service": {
          "other_platform_oauth_client": [
            {
              "client_id": "",
              "client_type": 3
            },
            {
              "client_id": "",
              "client_type": 2,
              "ios_info": {
                "bundle_id": "net.openkochi.yatri.debug"
              }
            }
          ]
        }
      }
    },
    {
      "client_info": {
        "mobilesdk_app_id": "1:123456789012:android:1234567890123456789012",
        "android_client_info": {
          "package_name": "in.juspay.nammayatripartner.debug"
        }
      },
      "oauth_client": [
        {
          "client_id": "",
          "client_type": 3
        }
      ],
      "api_key": [
        {
          "current_key": ""
        }
      ],
      "services": {
        "appinvite_service": {
          "other_platform_oauth_client": [
            {
              "client_id": "",
              "client_type": 3
            },
            {
              "client_id": "",
              "client_type": 2,
              "ios_info": {
                "bundle_id": "net.openkochi.yatri.debug"
              }
            }
          ]
        }
      }
    },
    {
      "client_info": {
        "mobilesdk_app_id": "1:123456789012:android:1234567890123456789012",
        "android_client_info": {
          "package_name": "in.mobility.manayatri.debug"
        }
      },
      "oauth_client": [
        {
          "client_id": "",
          "client_type": 3
        }
      ],
      "api_key": [
        {
          "current_key": ""
        }
      ],
      "services": {
        "appinvite_service": {
          "other_platform_oauth_client": [
            {
              "client_id": "",
              "client_type": 3
            },
            {
              "client_id": "",
              "client_type": 2,
              "ios_info": {
                "bundle_id": "net.openkochi.yatri.debug"
              }
            }
          ]
        }
      }
    },
    {
      "client_info": {
        "mobilesdk_app_id": "1:123456789012:android:1234567890123456789012",
        "android_client_info": {
          "package_name": "in.mobility.manayatripartner.debug"
        }
      },
      "oauth_client": [
        {
          "client_id": "",
          "client_type": 3
        }
      ],
      "api_key": [
        {
          "current_key": ""
        }
      ],
      "services": {
        "appinvite_service": {
          "other_platform_oauth_client": [
            {
              "client_id": "",
              "client_type": 3
            },
            {
              "client_id": "",
              "client_type": 2,
              "ios_info": {
                "bundle_id": "net.openkochi.yatri.debug"
              }
            }
          ]
        }
      }
    },
    {
      "client_info": {
        "mobilesdk_app_id": "1:123456789012:android:1234567890123456789012",
        "android_client_info": {
          "package_name": "net.openkochi.yatri.debug"
        }
      },
      "oauth_client": [
        {
          "client_id": "",
          "client_type": 3
        }
      ],
      "api_key": [
        {
          "current_key": ""
        }
      ],
      "services": {
        "appinvite_service": {
          "other_platform_oauth_client": [
            {
              "client_id": "",
              "client_type": 3
            },
            {
              "client_id": "",
              "client_type": 2,
              "ios_info": {
                "bundle_id": "net.openkochi.yatri.debug"
              }
            }
          ]
        }
      }
    },
    {
      "client_info": {
        "mobilesdk_app_id": "1:123456789012:android:1234567890123456789012",
        "android_client_info": {
          "package_name": "net.openkochi.yatripartner.debug"
        }
      },
      "oauth_client": [
        {
          "client_id": "",
          "client_type": 3
        }
      ],
      "api_key": [
        {
          "current_key": ""
        }
      ],
      "services": {
        "appinvite_service": {
          "other_platform_oauth_client": [
            {
              "client_id": "",
              "client_type": 3
            },
            {
              "client_id": "",
              "client_type": 2,
              "ios_info": {
                "bundle_id": "net.openkochi.yatri.debug"
              }
            }
          ]
        }
      }
    },
    {
      "client_info": {
        "mobilesdk_app_id": "1:123456789012:android:1234567890123456789012",
        "android_client_info": {
          "package_name": "in.juspay.jatrisaathi"
        }
      },
      "oauth_client": [
        {
          "client_id": "",
          "client_type": 3
        }
      ],
      "api_key": [
        {
          "current_key": ""
        }
      ],
      "services": {
        "appinvite_service": {
          "other_platform_oauth_client": [
            {
              "client_id": "",
              "client_type": 3
            },
            {
              "client_id": "",
              "client_type": 2,
              "ios_info": {
                "bundle_id": "in.juspay.nammayatri"
              }
            }
          ]
        }
      }
    },
    {
      "client_info": {
        "mobilesdk_app_id": "1:123456789012:android:1234567890123456789012",
        "android_client_info": {
          "package_name": "in.juspay.jatrisaathidriver"
        }
      },
      "oauth_client": [
        {
          "client_id": "",
          "client_type": 3
        }
      ],
      "api_key": [
        {
          "current_key": ""
        }
      ],
      "services": {
        "appinvite_service": {
          "other_platform_oauth_client": [
            {
              "client_id": "",
              "client_type": 3
            },
            {
              "client_id": "",
              "client_type": 2,
              "ios_info": {
                "bundle_id": "in.juspay.nammayatri"
              }
            }
          ]
        }
      }
    },
    {
      "client_info": {
        "mobilesdk_app_id": "1:123456789012:android:1234567890123456789012",
        "android_client_info": {
          "package_name": "in.juspay.nammayatri"
        }
      },
      "oauth_client": [
        {
          "client_id": "",
          "client_type": 3
        }
      ],
      "api_key": [
        {
          "current_key": ""
        }
      ],
      "services": {
        "appinvite_service": {
          "other_platform_oauth_client": [
            {
              "client_id": "",
              "client_type": 3
            },
            {
              "client_id": "",
              "client_type": 2,
              "ios_info": {
                "bundle_id": "in.juspay.nammayatri"
              }
            }
          ]
        }
      }
    },
    {
      "client_info": {
        "mobilesdk_app_id": "1:123456789012:android:1234567890123456789012",
        "android_client_info": {
          "package_name": "in.juspay.nammayatripartner"
        }
      },
      "oauth_client": [
        {
          "client_id": "",
          "client_type": 3
        }
      ],
      "api_key": [
        {
          "current_key": ""
        }
      ],
      "services": {
        "appinvite_service": {
          "other_platform_oauth_client": [
            {
              "client_id": "",
              "client_type": 3
            },
            {
              "client_id": "",
              "client_type": 2,
              "ios_info": {
                "bundle_id": "in.juspay.nammayatri"
              }
            }
          ]
        }
      }
    },
    {
      "client_info": {
        "mobilesdk_app_id": "1:123456789012:android:1234567890123456789012",
        "android_client_info": {
          "package_name": "in.mobility.manayatri"
        }
      },
      "oauth_client": [
        {
          "client_id": "",
          "client_type": 3
        }
      ],
      "api_key": [
        {
          "current_key": ""
        }
      ],
      "services": {
        "appinvite_service": {
          "other_platform_oauth_client": [
            {
              "client_id": "",
              "client_type": 3
            },
            {
              "client_id": "",
              "client_type": 2,
              "ios_info": {
                "bundle_id": "in.juspay.nammayatri"
              }
            }
          ]
        }
      }
    },
    {
      "client_info": {
        "mobilesdk_app_id": "1:123456789012:android:1234567890123456789012",
        "android_client_info": {
          "package_name": "in.mobility.manayatripartner"
        }
      },
      "oauth_client": [
        {
          "client_id": "",
          "client_type": 3
        }
      ],
      "api_key": [
        {
          "current_key": ""
        }
      ],
      "services": {
        "appinvite_service": {
          "other_platform_oauth_client": [
            {
              "client_id": "",
              "client_type": 3
            },
            {
              "client_id": "",
              "client_type": 2,
              "ios_info": {
                "bundle_id": "in.juspay.nammayatri"
              }
            }
          ]
        }
      }
    },
    {
      "client_info": {
        "mobilesdk_app_id": "1:123456789012:android:1234567890123456789012",
        "android_client_info": {
          "package_name": "net.openkochi.yatripartner"
        }
      },
      "oauth_client": [
        {
          "client_id": "",
          "client_type": 3
        }
      ],
      "api_key": [
        {
          "current_key": ""
        }
      ],
      "services": {
        "appinvite_service": {
          "other_platform_oauth_client": [
            {
              "client_id": "",
              "client_type": 3
            },
            {
              "client_id": "",
              "client_type": 2,
              "ios_info": {
                "bundle_id": "net.openkochi.yatri"
              }
            }
          ]
        }
      }
    },
    {
      "client_info": {
        "mobilesdk_app_id": "1:123456789012:android:1234567890123456789012",
        "android_client_info": {
          "package_name": "net.openkochi.yatri"
        }
      },
      "oauth_client": [
        {
          "client_id": "",
          "client_type": 3
        }
      ],
      "api_key": [
        {
          "current_key": ""
        }
      ],
      "services": {
        "appinvite_service": {
          "other_platform_oauth_client": [
            {
              "client_id": "",
              "client_type": 3
            },
            {
              "client_id": "",
              "client_type": 2,
              "ios_info": {
                "bundle_id": "net.openkochi.yatri"
              }
            }
          ]
        }
      }
    }
  ],
  "configuration_version": "1"
}