{
   "images" : {
      "app_notification_background" : true,
      "bubble_message_shape_left" : true,
      "bubble_message_shape_right" : true,
      "dashed_line" : true,
      "drawable" : true,
      "ic_agency_cancelled" : true,
      "ic_agency_offline" : true,
      "ic_app_update" : true,
      "ic_audio_loader" : true,
      "ic_grey_border" : true,
      "ic_invoice_border" : true,
      "ic_line" : true,
      "ic_loader" : true,
      "ic_pause" : true,
      "ic_play" : true,
      "ic_ride_not_found" : true,
      "ic_roundcorner_overlay" : true,
      "ic_share_location" : true,
      "label_shadow" : true,
      "loader_overlay" : true,
      "ny_ic_auto" : true,
      "ny_ic_call" : true,
      "ny_ic_chevron_down" : true,
      "ny_ic_chevron_left" : true,
      "ny_ic_chevron_up" : true,
      "ny_ic_circle" : true,
      "ny_ic_clip_board" : true,
      "ny_ic_close" : true,
      "ny_ic_close_filled_round" : true,
      "ny_ic_close_transparent" : true,
      "ny_ic_copy" : true,
      "ny_ic_dest_marker" : true,
      "ny_ic_green_circle" : true,
      "ny_ic_icon" : true,
      "ny_ic_invoice_logo" : true,
      "ny_ic_loc_red" : true,
      "ny_ic_location_access" : true,
      "ny_ic_location_track" : true,
      "ny_ic_message_square" : true,
      "ny_ic_namma_yatri_text_with_logo" : true,
      "ny_ic_next_ride" : true,
      "ny_ic_no_past_rides" : true,
      "ny_ic_offline" : true,
      "ny_ic_parallel_arrows" : true,
      "ny_ic_pin_drop_mark" : true,
      "ny_ic_profile_image" : true,
      "ny_ic_radio_button" : true,
      "ny_ic_radio_selected" : true,
      "ny_ic_radio_unselected" : true,
      "ny_ic_recenter_btn" : true,
      "ny_ic_red_circle" : true,
      "ny_ic_ride_completed" : true,
      "ny_ic_ride_end_red" : true,
      "ny_ic_ride_start_green" : true,
      "ny_ic_settings" : true,
      "ny_ic_shimmer_img" : true,
      "ny_ic_source_dot" : true,
      "ny_ic_splash_bg" : true,
      "ny_ic_src_marker" : true,
      "ny_ic_star_active" : true,
      "ny_ic_star_inactive" : true,
      "ny_ic_tick_white" : true,
      "ny_ic_vertical_line" : true,
      "popup_background" : true,
      "progress_circle" : true,
      "progress_loader" : true,
      "progressbar_clip" : true,
      "rotate_drawable" : true,
      "round_circle" : true,
      "round_corner_layout" : true,
      "rounded_corner_background" : true,
      "widget_close_gradient" : true
   }
}
