{"snappedPoints":[{"originalIndex":0,"location":{"latitude":10.060973611582504,"longitude":76.28765659910272},"placeId":"ChIJtwu94gkOCDsRP6oHIcBku38"},{"originalIndex":1,"location":{"latitude":10.060973350344904,"longitude":76.28765615293253},"placeId":"ChIJtwu94gkOCDsRP6oHIcBku38"},{"originalIndex":null,"location":{"latitude":10.0607979,"longitude":76.2873565},"placeId":"ChIJtwu94gkOCDsRP6oHIcBku38"},{"originalIndex":null,"location":{"latitude":10.0607979,"longitude":76.2873565},"placeId":"ChIJU0CodOINCDsRaw2qFMCJJ70"},{"originalIndex":null,"location":{"latitude":10.0607679,"longitude":76.2872905},"placeId":"ChIJU0CodOINCDsRaw2qFMCJJ70"},{"originalIndex":2,"location":{"latitude":10.060679718126776,"longitude":76.28714704183072},"placeId":"ChIJU0CodOINCDsRaw2qFMCJJ70"},{"originalIndex":null,"location":{"latitude":10.0606323,"longitude":76.28706989999999},"placeId":"ChIJU0CodOINCDsRaw2qFMCJJ70"},{"originalIndex":null,"location":{"latitude":10.0604771,"longitude":76.2868301},"placeId":"ChIJU0CodOINCDsRaw2qFMCJJ70"},{"originalIndex":null,"location":{"latitude":10.060298999999999,"longitude":76.2865858},"placeId":"ChIJU0CodOINCDsRaw2qFMCJJ70"},{"originalIndex":null,"location":{"latitude":10.0602001,"longitude":76.2864773},"placeId":"ChIJU0CodOINCDsRaw2qFMCJJ70"},{"originalIndex":null,"location":{"latitude":10.0602001,"longitude":76.2864773},"placeId":"ChIJWaHHceINCDsR2Uvz6r7RN5M"},{"originalIndex":null,"location":{"latitude":10.060054400000002,"longitude":76.28629719999999},"placeId":"ChIJWaHHceINCDsR2Uvz6r7RN5M"},{"originalIndex":null,"location":{"latitude":10.060054400000002,"longitude":76.28629719999999},"placeId":"ChIJK_Ab_eINCDsRiHwF0ue6_kk"},{"originalIndex":3,"location":{"latitude":10.060003283629834,"longitude":76.28624322474703},"placeId":"ChIJK_Ab_eINCDsRiHwF0ue6_kk"},{"originalIndex":null,"location":{"latitude":10.0597558,"longitude":76.2859819},"placeId":"ChIJK_Ab_eINCDsRiHwF0ue6_kk"},{"originalIndex":null,"location":{"latitude":10.059469499999999,"longitude":76.2857243},"placeId":"ChIJK_Ab_eINCDsRiHwF0ue6_kk"},{"originalIndex":null,"location":{"latitude":10.059201,"longitude":76.2855131},"placeId":"ChIJK_Ab_eINCDsRiHwF0ue6_kk"},{"originalIndex":null,"location":{"latitude":10.059037499999999,"longitude":76.2853974},"placeId":"ChIJK_Ab_eINCDsRiHwF0ue6_kk"},{"originalIndex":4,"location":{"latitude":10.058923352353359,"longitude":76.28532610605706},"placeId":"ChIJK_Ab_eINCDsRiHwF0ue6_kk"},{"originalIndex":null,"location":{"latitude":10.0586249,"longitude":76.2851397},"placeId":"ChIJK_Ab_eINCDsRiHwF0ue6_kk"},{"originalIndex":null,"location":{"latitude":10.058493200000001,"longitude":76.2850675},"placeId":"ChIJK_Ab_eINCDsRiHwF0ue6_kk"},{"originalIndex":null,"location":{"latitude":10.058370699999998,"longitude":76.2850062},"placeId":"ChIJK_Ab_eINCDsRiHwF0ue6_kk"},{"originalIndex":null,"location":{"latitude":10.0580769,"longitude":76.28487419999999},"placeId":"ChIJK_Ab_eINCDsRiHwF0ue6_kk"},{"originalIndex":null,"location":{"latitude":10.0580769,"longitude":76.28487419999999},"placeId":"ChIJ3Zq9HOMNCDsR2OAoZHbIzqI"},{"originalIndex":null,"location":{"latitude":10.0576283,"longitude":76.2846777},"placeId":"ChIJ3Zq9HOMNCDsR2OAoZHbIzqI"},{"originalIndex":5,"location":{"latitude":10.057516210393787,"longitude":76.28462422373772},"placeId":"ChIJ3Zq9HOMNCDsR2OAoZHbIzqI"},{"originalIndex":null,"location":{"latitude":10.0574952,"longitude":76.2846142},"placeId":"ChIJ3Zq9HOMNCDsR2OAoZHbIzqI"},{"originalIndex":null,"location":{"latitude":10.0574952,"longitude":76.2846142},"placeId":"ChIJjwcpEeMNCDsRBELORnAElak"},{"originalIndex":null,"location":{"latitude":10.056914199999998,"longitude":76.28438249999999},"placeId":"ChIJjwcpEeMNCDsRBELORnAElak"},{"originalIndex":null,"location":{"latitude":10.056914199999998,"longitude":76.28438249999999},"placeId":"ChIJo_FbQuMNCDsR6C-miAjQTi4"},{"originalIndex":null,"location":{"latitude":10.0568524,"longitude":76.2843568},"placeId":"ChIJo_FbQuMNCDsR6C-miAjQTi4"},{"originalIndex":null,"location":{"latitude":10.056210799999999,"longitude":76.2840591},"placeId":"ChIJo_FbQuMNCDsR6C-miAjQTi4"},{"originalIndex":6,"location":{"latitude":10.05609344130864,"longitude":76.28399598033857},"placeId":"ChIJo_FbQuMNCDsR6C-miAjQTi4"},{"originalIndex":null,"location":{"latitude":10.0559161,"longitude":76.2839006},"placeId":"ChIJo_FbQuMNCDsR6C-miAjQTi4"},{"originalIndex":null,"location":{"latitude":10.055513399999999,"longitude":76.2836547},"placeId":"ChIJo_FbQuMNCDsR6C-miAjQTi4"},{"originalIndex":null,"location":{"latitude":10.0554533,"longitude":76.28361389999999},"placeId":"ChIJo_FbQuMNCDsR6C-miAjQTi4"},{"originalIndex":null,"location":{"latitude":10.0554533,"longitude":76.28361389999999},"placeId":"ChIJwSv4WOMNCDsRuPzinosTgPo"},{"originalIndex":null,"location":{"latitude":10.055360700000001,"longitude":76.2835515},"placeId":"ChIJwSv4WOMNCDsRuPzinosTgPo"},{"originalIndex":null,"location":{"latitude":10.055360700000001,"longitude":76.2835515},"placeId":"ChIJdSzqqOQNCDsRZGmjmnKgfss"},{"originalIndex":null,"location":{"latitude":10.055100200000002,"longitude":76.28336860000002},"placeId":"ChIJdSzqqOQNCDsRZGmjmnKgfss"},{"originalIndex":7,"location":{"latitude":10.054788176917638,"longitude":76.28311255446054},"placeId":"ChIJdSzqqOQNCDsRZGmjmnKgfss"},{"originalIndex":null,"location":{"latitude":10.054769099999998,"longitude":76.2830969},"placeId":"ChIJdSzqqOQNCDsRZGmjmnKgfss"},{"originalIndex":null,"location":{"latitude":10.0544344,"longitude":76.28276749999999},"placeId":"ChIJdSzqqOQNCDsRZGmjmnKgfss"},{"originalIndex":null,"location":{"latitude":10.0543923,"longitude":76.2827315},"placeId":"ChIJdSzqqOQNCDsRZGmjmnKgfss"},{"originalIndex":null,"location":{"latitude":10.0543923,"longitude":76.2827315},"placeId":"ChIJQQ6bSfsNCDsRWttFlReH5tk"},{"originalIndex":null,"location":{"latitude":10.054212299999998,"longitude":76.2825383},"placeId":"ChIJQQ6bSfsNCDsRWttFlReH5tk"},{"originalIndex":null,"location":{"latitude":10.0539721,"longitude":76.28226769999999},"placeId":"ChIJQQ6bSfsNCDsRWttFlReH5tk"},{"originalIndex":null,"location":{"latitude":10.053821899999999,"longitude":76.2820784},"placeId":"ChIJQQ6bSfsNCDsRWttFlReH5tk"},{"originalIndex":8,"location":{"latitude":10.053756845338498,"longitude":76.28199435136452},"placeId":"ChIJQQ6bSfsNCDsRWttFlReH5tk"},{"originalIndex":null,"location":{"latitude":10.0535592,"longitude":76.281739},"placeId":"ChIJQQ6bSfsNCDsRWttFlReH5tk"},{"originalIndex":null,"location":{"latitude":10.0535592,"longitude":76.281739},"placeId":"ChIJsQ8mGPsNCDsRzDXeIsqMUcQ"},{"originalIndex":null,"location":{"latitude":10.053490199999999,"longitude":76.28163339999999},"placeId":"ChIJsQ8mGPsNCDsRzDXeIsqMUcQ"},{"originalIndex":null,"location":{"latitude":10.0528918,"longitude":76.28077809999999},"placeId":"ChIJsQ8mGPsNCDsRzDXeIsqMUcQ"},{"originalIndex":9,"location":{"latitude":10.05289156328757,"longitude":76.28077779431861},"placeId":"ChIJsQ8mGPsNCDsRzDXeIsqMUcQ"},{"originalIndex":null,"location":{"latitude":10.052633700000001,"longitude":76.2804448},"placeId":"ChIJsQ8mGPsNCDsRzDXeIsqMUcQ"},{"originalIndex":null,"location":{"latitude":10.052633700000001,"longitude":76.2804448},"placeId":"ChIJoWUFP_oNCDsR3BjMfxJ4D0g"},{"originalIndex":null,"location":{"latitude":10.052574199999999,"longitude":76.2803765},"placeId":"ChIJoWUFP_oNCDsR3BjMfxJ4D0g"},{"originalIndex":10,"location":{"latitude":10.052138070826388,"longitude":76.27981961604405},"placeId":"ChIJoWUFP_oNCDsR3BjMfxJ4D0g"},{"originalIndex":null,"location":{"latitude":10.0520003,"longitude":76.2796437},"placeId":"ChIJoWUFP_oNCDsR3BjMfxJ4D0g"},{"originalIndex":null,"location":{"latitude":10.051948999999999,"longitude":76.279572},"placeId":"ChIJoWUFP_oNCDsR3BjMfxJ4D0g"},{"originalIndex":null,"location":{"latitude":10.0515879,"longitude":76.27897519999999},"placeId":"ChIJoWUFP_oNCDsR3BjMfxJ4D0g"},{"originalIndex":11,"location":{"latitude":10.051507498048009,"longitude":76.27883533690462},"placeId":"ChIJoWUFP_oNCDsR3BjMfxJ4D0g"},{"originalIndex":null,"location":{"latitude":10.051442,"longitude":76.2787214},"placeId":"ChIJoWUFP_oNCDsR3BjMfxJ4D0g"},{"originalIndex":null,"location":{"latitude":10.0512104,"longitude":76.27828339999999},"placeId":"ChIJoWUFP_oNCDsR3BjMfxJ4D0g"},{"originalIndex":null,"location":{"latitude":10.051114600000002,"longitude":76.2781085},"placeId":"ChIJoWUFP_oNCDsR3BjMfxJ4D0g"},{"originalIndex":null,"location":{"latitude":10.051114600000002,"longitude":76.2781085},"placeId":"ChIJ7045GPoNCDsRck6AbiE-OZU"},{"originalIndex":null,"location":{"latitude":10.051101499999998,"longitude":76.2780865},"placeId":"ChIJ7045GPoNCDsRck6AbiE-OZU"},{"originalIndex":12,"location":{"latitude":10.051025791850893,"longitude":76.27794751925072},"placeId":"ChIJ7045GPoNCDsRck6AbiE-OZU"},{"originalIndex":null,"location":{"latitude":10.050949299999997,"longitude":76.27780709999999},"placeId":"ChIJ7045GPoNCDsRck6AbiE-OZU"},{"originalIndex":null,"location":{"latitude":10.050735800000002,"longitude":76.2774038},"placeId":"ChIJ7045GPoNCDsRck6AbiE-OZU"},{"originalIndex":13,"location":{"latitude":10.050627025052822,"longitude":76.27718659504603},"placeId":"ChIJ7045GPoNCDsRck6AbiE-OZU"},{"originalIndex":null,"location":{"latitude":10.050515199999998,"longitude":76.27696329999999},"placeId":"ChIJ7045GPoNCDsRck6AbiE-OZU"},{"originalIndex":null,"location":{"latitude":10.050515199999998,"longitude":76.27696329999999},"placeId":"ChIJJxXAHfoNCDsRDIaysrqQ2mE"},{"originalIndex":null,"location":{"latitude":10.0504457,"longitude":76.2769974},"placeId":"ChIJJxXAHfoNCDsRDIaysrqQ2mE"},{"originalIndex":null,"location":{"latitude":10.0504457,"longitude":76.2769974},"placeId":"ChIJif8z3PkNCDsRDV8TwaQ-Z90"},{"originalIndex":14,"location":{"latitude":10.050354569216262,"longitude":76.2767880731089},"placeId":"ChIJif8z3PkNCDsRDV8TwaQ-Z90"},{"originalIndex":15,"location":{"latitude":10.050323942480713,"longitude":76.27671772376608},"placeId":"ChIJif8z3PkNCDsRDV8TwaQ-Z90"},{"originalIndex":null,"location":{"latitude":10.0501733,"longitude":76.2763717},"placeId":"ChIJif8z3PkNCDsRDV8TwaQ-Z90"},{"originalIndex":null,"location":{"latitude":10.0501733,"longitude":76.2763717},"placeId":"ChIJif8z3PkNCDsR5QmJqRG0YrQ"},{"originalIndex":16,"location":{"latitude":10.050016030222594,"longitude":76.27596796986104},"placeId":"ChIJif8z3PkNCDsR5QmJqRG0YrQ"},{"originalIndex":null,"location":{"latitude":10.050010900000002,"longitude":76.2759548},"placeId":"ChIJif8z3PkNCDsR5QmJqRG0YrQ"},{"originalIndex":null,"location":{"latitude":10.0498651,"longitude":76.2755998},"placeId":"ChIJif8z3PkNCDsR5QmJqRG0YrQ"},{"originalIndex":null,"location":{"latitude":10.049811099999998,"longitude":76.2754413},"placeId":"ChIJif8z3PkNCDsR5QmJqRG0YrQ"},{"originalIndex":17,"location":{"latitude":10.049791309168398,"longitude":76.2753698757393},"placeId":"ChIJif8z3PkNCDsR5QmJqRG0YrQ"},{"originalIndex":null,"location":{"latitude":10.0497262,"longitude":76.2751349},"placeId":"ChIJif8z3PkNCDsR5QmJqRG0YrQ"},{"originalIndex":null,"location":{"latitude":10.049605099999999,"longitude":76.274743},"placeId":"ChIJif8z3PkNCDsR5QmJqRG0YrQ"},{"originalIndex":18,"location":{"latitude":10.049576388344335,"longitude":76.27465635155579},"placeId":"ChIJif8z3PkNCDsR5QmJqRG0YrQ"},{"originalIndex":null,"location":{"latitude":10.0495324,"longitude":76.2745236},"placeId":"ChIJif8z3PkNCDsR5QmJqRG0YrQ"},{"originalIndex":null,"location":{"latitude":10.049418899999997,"longitude":76.2740677},"placeId":"ChIJif8z3PkNCDsR5QmJqRG0YrQ"},{"originalIndex":19,"location":{"latitude":10.049376114284211,"longitude":76.27388934106071},"placeId":"ChIJif8z3PkNCDsR5QmJqRG0YrQ"},{"originalIndex":20,"location":{"latitude":10.049296631917292,"longitude":76.2735580075801},"placeId":"ChIJif8z3PkNCDsR5QmJqRG0YrQ"},{"originalIndex":null,"location":{"latitude":10.0492671,"longitude":76.2734349},"placeId":"ChIJif8z3PkNCDsR5QmJqRG0YrQ"},{"originalIndex":null,"location":{"latitude":10.0492671,"longitude":76.2734349},"placeId":"ChIJda7siPcNCDsRDzQ6ngQ1rPc"},{"originalIndex":null,"location":{"latitude":10.0492096,"longitude":76.2731428},"placeId":"ChIJda7siPcNCDsRDzQ6ngQ1rPc"},{"originalIndex":null,"location":{"latitude":10.049194499999999,"longitude":76.2730722},"placeId":"ChIJda7siPcNCDsRDzQ6ngQ1rPc"},{"originalIndex":null,"location":{"latitude":10.0491808,"longitude":76.2730464},"placeId":"ChIJda7siPcNCDsRDzQ6ngQ1rPc"},{"originalIndex":null,"location":{"latitude":10.049156199999999,"longitude":76.2730134},"placeId":"ChIJda7siPcNCDsRDzQ6ngQ1rPc"},{"originalIndex":21,"location":{"latitude":10.049106854746205,"longitude":76.27297066097347},"placeId":"ChIJda7siPcNCDsRDzQ6ngQ1rPc"},{"originalIndex":null,"location":{"latitude":10.048997100000001,"longitude":76.27287559999999},"placeId":"ChIJda7siPcNCDsRDzQ6ngQ1rPc"},{"originalIndex":null,"location":{"latitude":10.048997100000001,"longitude":76.27287559999999},"placeId":"ChIJjZxqjvcNCDsRvhGLVgBuf9o"},{"originalIndex":null,"location":{"latitude":10.0487364,"longitude":76.2730205},"placeId":"ChIJjZxqjvcNCDsRvhGLVgBuf9o"},{"originalIndex":null,"location":{"latitude":10.0486678,"longitude":76.27305179999999},"placeId":"ChIJjZxqjvcNCDsRvhGLVgBuf9o"},{"originalIndex":22,"location":{"latitude":10.048627817181956,"longitude":76.2730683710515},"placeId":"ChIJjZxqjvcNCDsRvhGLVgBuf9o"},{"originalIndex":null,"location":{"latitude":10.0486,"longitude":76.27307990000001},"placeId":"ChIJjZxqjvcNCDsRvhGLVgBuf9o"},{"originalIndex":null,"location":{"latitude":10.0486,"longitude":76.27307990000001},"placeId":"ChIJLWafl_cNCDsRin5vD3xiE_g"},{"originalIndex":null,"location":{"latitude":10.0484736,"longitude":76.2731123},"placeId":"ChIJLWafl_cNCDsRin5vD3xiE_g"},{"originalIndex":23,"location":{"latitude":10.047999038531385,"longitude":76.27320221911062},"placeId":"ChIJLWafl_cNCDsRin5vD3xiE_g"},{"originalIndex":null,"location":{"latitude":10.0477722,"longitude":76.27324519999999},"placeId":"ChIJLWafl_cNCDsRin5vD3xiE_g"},{"originalIndex":null,"location":{"latitude":10.0477722,"longitude":76.27324519999999},"placeId":"ChIJKSjurfcNCDsRVQT3-FCqG1E"},{"originalIndex":24,"location":{"latitude":10.047414791432804,"longitude":76.2732861293181},"placeId":"ChIJKSjurfcNCDsRVQT3-FCqG1E"},{"originalIndex":25,"location":{"latitude":10.046748041256153,"longitude":76.27336248323239},"placeId":"ChIJKSjurfcNCDsRVQT3-FCqG1E"},{"originalIndex":26,"location":{"latitude":10.046201858055195,"longitude":76.27342502999932},"placeId":"ChIJKSjurfcNCDsRVQT3-FCqG1E"},{"originalIndex":null,"location":{"latitude":10.046075499999999,"longitude":76.2734395},"placeId":"ChIJKSjurfcNCDsRVQT3-FCqG1E"},{"originalIndex":null,"location":{"latitude":10.046075499999999,"longitude":76.2734395},"placeId":"ChIJGSfkY_YNCDsRz8G-5AmR8S0"},{"originalIndex":null,"location":{"latitude":10.045892499999999,"longitude":76.2734688},"placeId":"ChIJGSfkY_YNCDsRz8G-5AmR8S0"},{"originalIndex":null,"location":{"latitude":10.0457637,"longitude":76.2734947},"placeId":"ChIJGSfkY_YNCDsRz8G-5AmR8S0"},{"originalIndex":27,"location":{"latitude":10.04563752010239,"longitude":76.27352710345508},"placeId":"ChIJGSfkY_YNCDsRz8G-5AmR8S0"},{"originalIndex":null,"location":{"latitude":10.0455616,"longitude":76.2735466},"placeId":"ChIJGSfkY_YNCDsRz8G-5AmR8S0"},{"originalIndex":null,"location":{"latitude":10.045189299999999,"longitude":76.273628},"placeId":"ChIJGSfkY_YNCDsRz8G-5AmR8S0"},{"originalIndex":null,"location":{"latitude":10.044981700000001,"longitude":76.2736845},"placeId":"ChIJGSfkY_YNCDsRz8G-5AmR8S0"},{"originalIndex":28,"location":{"latitude":10.044975334367424,"longitude":76.27368603219782},"placeId":"ChIJGSfkY_YNCDsRz8G-5AmR8S0"},{"originalIndex":29,"location":{"latitude":10.044435406348414,"longitude":76.27381599180325},"placeId":"ChIJGSfkY_YNCDsRz8G-5AmR8S0"},{"originalIndex":null,"location":{"latitude":10.044162,"longitude":76.2738818},"placeId":"ChIJGSfkY_YNCDsRz8G-5AmR8S0"},{"originalIndex":30,"location":{"latitude":10.043939231237118,"longitude":76.27394042001394},"placeId":"ChIJGSfkY_YNCDsRz8G-5AmR8S0"}]}